zippity/__init__.py
zippity/names.py
zippity-0.0.dist-info/DESCRIPTION.rst
zippity-0.0.dist-info/METADATA
zippity-0.0.dist-info/RECORD
zippity-0.0.dist-info/WHEEL
zippity-0.0.dist-info/metadata.json
zippity-0.0.dist-info/top_level.txt
