Metadata-Version: 2.0
Name: zippity
Version: 0.0
Summary: A simple zip file-based persistence library
Home-page: UNKNOWN
Author: Aaron Hosford
Author-email: hosford42@gmail.com
License: MIT
Platform: UNKNOWN
